regression_model/VERSION
regression_model/__init__.py
regression_model/config.yml
regression_model/predict.py
regression_model/train_pipeline.py
regression_model/config/__init__.py
regression_model/config/core.py
regression_model/processing/__init__.py
regression_model/processing/data_manager.py
regression_model/processing/features_preprocessing.py
regression_model/processing/validation.py
regression_model/trained_models/__init__.py
regression_model/trained_models/model_0.1.0.pkl
production_titanic_model-0.1.0.dist-info/METADATA
production_titanic_model-0.1.0.dist-info/WHEEL
production_titanic_model-0.1.0.dist-info/top_level.txt
production_titanic_model-0.1.0.dist-info/RECORD
